{
  "generated_at": "2026-07-10T23:55:50.466Z",
  "top": [
    {
      "rank": 1,
      "id": 395,
      "nombre": "BRYAN RICARDO ORTEGA CADENA",
      "phone": "+525627474439",
      "email": "richie.odonto22@gmail.com",
      "segment": "nunca-agendo",
      "tratamiento_principal": "PROTESIS BUCAL",
      "tratamientos": [
        "PROTESIS BUCAL",
        "ENDODONCIA",
        "CONSULTA URGENCIA",
        "PROTESIS",
        "CIRUGIA",
        "ORTODONCIA",
        "TOMOGRAFIA"
      ],
      "treatment_tag": "protesis",
      "presupuesto_total": 165107.95,
      "abonado_total": 500,
      "deuda_total": 0,
      "reactivation_score": 125,
      "priority_band": "alta",
      "priority_reason": "nunca-agendo, protesis, presupuesto-alto, tiene-telefono",
      "elevator_id": "qGuE7Dx51rOAvaQ0wCNG",
      "elevator_sync_status": "created"
    },
    {
      "rank": 2,
      "id": 1602,
      "nombre": "SLENDY ZAPATA",
      "phone": "+14079732801",
      "email": "veteranomusicstudio@gmail.com",
      "segment": "nunca-agendo",
      "tratamiento_principal": "REMOCION DE CARILLAS",
      "tratamientos": [
        "REMOCION DE CARILLAS",
        "ESTETICA DENTAL"
      ],
      "treatment_tag": "estetica",
      "presupuesto_total": 278480,
      "abonado_total": 0,
      "deuda_total": 0,
      "reactivation_score": 119,
      "priority_band": "alta",
      "priority_reason": "nunca-agendo, estetica, presupuesto-alto, tiene-telefono",
      "elevator_id": "aJhtdG3XZLdq8DNPxiKq",
      "elevator_sync_status": "created"
    },
    {
      "rank": 3,
      "id": 1338,
      "nombre": "MONIKA GOLDEN",
      "phone": "+525613136364",
      "email": "mplf007@gmail.com",
      "segment": "nunca-agendo",
      "tratamiento_principal": "ORTODONCIA",
      "tratamientos": [
        "ORTODONCIA"
      ],
      "treatment_tag": "ortodoncia",
      "presupuesto_total": 86010,
      "abonado_total": 0,
      "deuda_total": 0,
      "reactivation_score": 117,
      "priority_band": "alta",
      "priority_reason": "nunca-agendo, ortodoncia, presupuesto-alto, tiene-telefono",
      "elevator_id": "IBnVc1zOksEccXrykf9r",
      "elevator_sync_status": "created"
    },
    {
      "rank": 4,
      "id": 317,
      "nombre": "MARITZA GOMEZ",
      "phone": "+523318349940",
      "email": "mari_tzago@yahoo.com.mx",
      "segment": "inactivo-90d",
      "tratamiento_principal": "REHABILITACION SOBRE IMPLANTE",
      "tratamientos": [
        "REHABILITACION SOBRE IMPLANTE",
        "CIRUGIA",
        "ESTETICA DENTAL",
        "ORTODONCIA",
        "ODONTOLOGIA GENERAL",
        "ALANA VILLAVICENCIO",
        "IMPLANTOLOGIA",
        "CRISTAL"
      ],
      "treatment_tag": "implantes",
      "presupuesto_total": 1008773,
      "abonado_total": 200,
      "deuda_total": 60545,
      "reactivation_score": 115,
      "priority_band": "alta",
      "priority_reason": "inactivo-90d, implantes, presupuesto-alto, deuda, tiene-telefono",
      "elevator_id": "Xk14LQEJChhfzO1TYpdG",
      "elevator_sync_status": "created"
    },
    {
      "rank": 5,
      "id": 2013,
      "nombre": "Karla Ariza",
      "phone": "+525611102657",
      "email": "arizak77@gmail.com",
      "segment": "nunca-agendo",
      "tratamiento_principal": "REHABILITACION DE CORONAS S/I",
      "tratamientos": [
        "REHABILITACION DE CORONAS S/I"
      ],
      "treatment_tag": "rehabilitacion",
      "presupuesto_total": 203500,
      "abonado_total": 0,
      "deuda_total": 0,
      "reactivation_score": 113,
      "priority_band": "alta",
      "priority_reason": "nunca-agendo, rehabilitacion, presupuesto-alto, tiene-telefono",
      "elevator_id": "mRR1x4h2eF5EiDmwHISr",
      "elevator_sync_status": "updated"
    },
    {
      "rank": 6,
      "id": 146,
      "nombre": "MONICA JOSE CATALAN",
      "phone": "+529622861978",
      "email": "monicacatalan13@gmail.com",
      "segment": "inactivo-90d",
      "tratamiento_principal": "CIRUGIA BUCAL",
      "tratamientos": [
        "CIRUGIA BUCAL",
        "ORTODONCIA",
        "ODONTOLOGIA GENERAL"
      ],
      "treatment_tag": "ortodoncia",
      "presupuesto_total": 128652.5,
      "abonado_total": 23730,
      "deuda_total": 19500,
      "reactivation_score": 110,
      "priority_band": "alta",
      "priority_reason": "inactivo-90d, ortodoncia, presupuesto-alto, deuda, tiene-telefono",
      "elevator_id": null,
      "elevator_sync_status": null
    },
    {
      "rank": 7,
      "id": 977,
      "nombre": "JANET JIMENEZ TORRES",
      "phone": "+525613688078",
      "email": "janetzitajimeneztorres38@gmail.com",
      "segment": "inactivo-30d",
      "tratamiento_principal": "DESTAPE DE IMPLANTE",
      "tratamientos": [
        "Nuevo plan de tratamiento",
        "DESTAPE DE IMPLANTE",
        "PRIMERA CITA",
        "CIRUGÍA",
        "ODONTOLOGIA GENERAL",
        "PROTESIS DENTAL DEFINITIVA",
        "ENDODONCIA",
        "IMPLANTOLOGIA"
      ],
      "treatment_tag": "implantes",
      "presupuesto_total": 187702.5,
      "abonado_total": 96366,
      "deuda_total": 0,
      "reactivation_score": 108,
      "priority_band": "alta",
      "priority_reason": "inactivo-30d, implantes, presupuesto-alto, tiene-telefono",
      "elevator_id": null,
      "elevator_sync_status": null
    },
    {
      "rank": 8,
      "id": 1185,
      "nombre": "DELMIRA SANCHEZ LEAL",
      "phone": "+17865850312",
      "email": "delmisanchez@gmail.com",
      "segment": "inactivo-30d",
      "tratamiento_principal": "DESTAPE DE IMPLANTES",
      "tratamientos": [
        "Nuevo plan de tratamiento",
        "DESTAPE DE IMPLANTES",
        "TOMOGRAFÍA",
        "CEPILLO CURAPROX",
        "PROVISIONAL",
        "CIRUGIA",
        "PRIMERA CONSULTA",
        "ODONTOLOGIA GENERAL"
      ],
      "treatment_tag": "implantes",
      "presupuesto_total": 210545,
      "abonado_total": 209065,
      "deuda_total": 0,
      "reactivation_score": 108,
      "priority_band": "alta",
      "priority_reason": "inactivo-30d, implantes, presupuesto-alto, tiene-telefono",
      "elevator_id": null,
      "elevator_sync_status": null
    },
    {
      "rank": 9,
      "id": 1773,
      "nombre": "RAUL GONZALEZ PEREZ",
      "phone": "+525554311958",
      "email": "gopr70@gmail.com",
      "segment": "inactivo-30d",
      "tratamiento_principal": "CORONA SOBRE IMPLANTE",
      "tratamientos": [
        "Nuevo plan de tratamiento",
        "CORONA SOBRE IMPLANTE",
        "CIRUGIA",
        "ODONTOLOGIA GENERAL",
        "PRIMERA CONSULTA"
      ],
      "treatment_tag": "implantes",
      "presupuesto_total": 253769,
      "abonado_total": 176419,
      "deuda_total": 0,
      "reactivation_score": 108,
      "priority_band": "alta",
      "priority_reason": "inactivo-30d, implantes, presupuesto-alto, tiene-telefono",
      "elevator_id": null,
      "elevator_sync_status": null
    },
    {
      "rank": 10,
      "id": 1892,
      "nombre": "RAFAEL PESCADOR",
      "phone": "+525543492504",
      "email": "rafapess@gmail.com",
      "segment": "inactivo-30d",
      "tratamiento_principal": "ODONTOLOGIA GENERAL",
      "tratamientos": [
        "ODONTOLOGIA GENERAL",
        "CEMENTACION CORONA (EXTERNA)",
        "PROTESIS SOBRE IMPLANTE",
        "IMPLANTOLOGIA",
        "CIRUGIA",
        "INVISALIGN",
        "PRIMERA CONSULTA"
      ],
      "treatment_tag": "implantes",
      "presupuesto_total": 226880,
      "abonado_total": 51265,
      "deuda_total": 0,
      "reactivation_score": 108,
      "priority_band": "alta",
      "priority_reason": "inactivo-30d, implantes, presupuesto-alto, tiene-telefono",
      "elevator_id": null,
      "elevator_sync_status": null
    },
    {
      "rank": 11,
      "id": 2035,
      "nombre": "DIANA L CRUZ",
      "phone": "+18455053355",
      "email": "jcampostax45@gmail.com",
      "segment": "inactivo-30d",
      "tratamiento_principal": "PROTESIS SOBRE IMPLANTE",
      "tratamientos": [
        "Nuevo plan de tratamiento",
        "PROTESIS SOBRE IMPLANTE",
        "CIRUGIA",
        "CIRUGIA (EXTRACCION)",
        "ODONTOLOGIA GENERAL",
        "CONSULTA"
      ],
      "treatment_tag": "implantes",
      "presupuesto_total": 165096,
      "abonado_total": 112302,
      "deuda_total": 0,
      "reactivation_score": 108,
      "priority_band": "alta",
      "priority_reason": "inactivo-30d, implantes, presupuesto-alto, tiene-telefono",
      "elevator_id": null,
      "elevator_sync_status": null
    },
    {
      "rank": 12,
      "id": 2465,
      "nombre": "SURY FIGUEREO",
      "phone": "+16463991888",
      "email": "suryfiguereo@gmail.com",
      "segment": "inactivo-30d",
      "tratamiento_principal": "ENDODONCIA",
      "tratamientos": [
        "Nuevo plan de tratamiento",
        "ENDODONCIA",
        "ODONTOLOGIA GENERAL",
        "IMPLANTOLOGIA",
        "CIRUGIA",
        "PROTESIS SOBRE IMPLANTE",
        "PRIMERA CONSULTA"
      ],
      "treatment_tag": "implantes",
      "presupuesto_total": 455677.65,
      "abonado_total": 214727.65,
      "deuda_total": 0,
      "reactivation_score": 108,
      "priority_band": "alta",
      "priority_reason": "inactivo-30d, implantes, presupuesto-alto, tiene-telefono",
      "elevator_id": null,
      "elevator_sync_status": null
    },
    {
      "rank": 13,
      "id": 2577,
      "nombre": "JAZMIN LASTRA LORA",
      "phone": "+525538997672",
      "email": "jazminlastra@hotmail.com",
      "segment": "inactivo-30d",
      "tratamiento_principal": "REHABILITACION SOBRE IMPLANTE",
      "tratamientos": [
        "REHABILITACION SOBRE IMPLANTE",
        "IMPLANTOLOGIA",
        "ENDODONCIA",
        "ODONTOLOGIA GENERAL",
        "CIRUGÍA",
        "PRIMERA CONSULTA"
      ],
      "treatment_tag": "implantes",
      "presupuesto_total": 133551,
      "abonado_total": 2000,
      "deuda_total": 0,
      "reactivation_score": 108,
      "priority_band": "alta",
      "priority_reason": "inactivo-30d, implantes, presupuesto-alto, tiene-telefono",
      "elevator_id": null,
      "elevator_sync_status": null
    },
    {
      "rank": 14,
      "id": 2585,
      "nombre": "LUIZ DA SILVA TAVARES",
      "phone": "+525561114301",
      "email": "lstbrasil@hotmail.com",
      "segment": "inactivo-30d",
      "tratamiento_principal": "PROTESIS SOBRE IMPLANTE",
      "tratamientos": [
        "PROTESIS SOBRE IMPLANTE",
        "IMPLANTOLOGIA",
        "CIRUGIA",
        "ODONTOLOGIA GENERAL",
        "PRIMERA CONSULTA"
      ],
      "treatment_tag": "implantes",
      "presupuesto_total": 134871,
      "abonado_total": 2000,
      "deuda_total": 0,
      "reactivation_score": 108,
      "priority_band": "alta",
      "priority_reason": "inactivo-30d, implantes, presupuesto-alto, tiene-telefono",
      "elevator_id": null,
      "elevator_sync_status": null
    },
    {
      "rank": 15,
      "id": 2596,
      "nombre": "PAOLO BRUCATO",
      "phone": "+523290098573",
      "email": "brucatopaolo@outlook.ct",
      "segment": "inactivo-30d",
      "tratamiento_principal": "CORONA SOBRE DIENTE",
      "tratamientos": [
        "CORONA SOBRE DIENTE",
        "REHABILITACIÓN IMPLANTES",
        "CIRUGIA",
        "REHABILITACION COMPLETA",
        "CONSULTA PROTESIS",
        "ODONTOLOGIA GENERAL",
        "PRIMERA CONSULTA"
      ],
      "treatment_tag": "implantes",
      "presupuesto_total": 522586,
      "abonado_total": 7500,
      "deuda_total": 0,
      "reactivation_score": 108,
      "priority_band": "alta",
      "priority_reason": "inactivo-30d, implantes, presupuesto-alto, tiene-telefono",
      "elevator_id": null,
      "elevator_sync_status": null
    },
    {
      "rank": 16,
      "id": 45,
      "nombre": "ANA PAULA FERNANDEZ BERNAL",
      "phone": "+525523002679",
      "email": "apforas@gmail.com",
      "segment": "inactivo-90d",
      "tratamiento_principal": "ODONTOLOGIA GENERAL",
      "tratamientos": [
        "ODONTOLOGIA GENERAL",
        "TOMOGRAFÍA",
        "CONSULTA",
        "ENDODONCIA",
        "REHABILITACION COMPLETA",
        "RETENCION",
        "CIRUGÍA",
        "ORTODONCIA"
      ],
      "treatment_tag": "ortodoncia",
      "presupuesto_total": 401422.25,
      "abonado_total": 3250,
      "deuda_total": 1350,
      "reactivation_score": 106,
      "priority_band": "alta",
      "priority_reason": "inactivo-90d, ortodoncia, presupuesto-alto, deuda, tiene-telefono",
      "elevator_id": null,
      "elevator_sync_status": null
    },
    {
      "rank": 17,
      "id": 126,
      "nombre": "VANESSA ABREU",
      "phone": "+525537269680",
      "email": "byvanessa@hotmail.com",
      "segment": "inactivo-90d",
      "tratamiento_principal": "ORTODONCIA",
      "tratamientos": [
        "ORTODONCIA",
        "PERIODONCIA",
        "ESTETICA. PRESUPUESTO"
      ],
      "treatment_tag": "ortodoncia",
      "presupuesto_total": 132500,
      "abonado_total": 121000,
      "deuda_total": 6500,
      "reactivation_score": 106,
      "priority_band": "alta",
      "priority_reason": "inactivo-90d, ortodoncia, presupuesto-alto, deuda, tiene-telefono",
      "elevator_id": null,
      "elevator_sync_status": null
    },
    {
      "rank": 18,
      "id": 362,
      "nombre": "NAYIVE CORZO",
      "phone": "+525591973636",
      "email": "nayive.corzo@hotmail.com",
      "segment": "inactivo-30d",
      "tratamiento_principal": "ODONTOLOGIA GENERAL",
      "tratamientos": [
        "Nuevo plan de tratamiento",
        "ODONTOLOGIA GENERAL",
        "RADIOGRAFIA",
        "CORONA OD 27",
        "ORTODONCIA",
        "TOMOGRAFIA",
        "CONSULTA DE VALORACION",
        "PROTESIS"
      ],
      "treatment_tag": "protesis",
      "presupuesto_total": 125530,
      "abonado_total": 69048,
      "deuda_total": 0,
      "reactivation_score": 105,
      "priority_band": "alta",
      "priority_reason": "inactivo-30d, protesis, presupuesto-alto, tiene-telefono",
      "elevator_id": null,
      "elevator_sync_status": null
    },
    {
      "rank": 19,
      "id": 630,
      "nombre": "LUIS PABLO  DE LOS COBOS",
      "phone": "+529841883209",
      "email": "luispablo@anant.mx",
      "segment": "inactivo-30d",
      "tratamiento_principal": "ODONTOLOGIA GENERAL",
      "tratamientos": [
        "ODONTOLOGIA GENERAL",
        "PROTESIS",
        "IMPLANTOLOGIA",
        "RTETIRO DE BRACKETS",
        "CONSULTA",
        "CIRUGIA BUCAL",
        "ESTETICA DENTAL",
        "CEPILLO CURAPROX"
      ],
      "treatment_tag": "protesis",
      "presupuesto_total": 364993,
      "abonado_total": 120839,
      "deuda_total": 0,
      "reactivation_score": 105,
      "priority_band": "alta",
      "priority_reason": "inactivo-30d, protesis, presupuesto-alto, tiene-telefono",
      "elevator_id": null,
      "elevator_sync_status": null
    },
    {
      "rank": 20,
      "id": 1140,
      "nombre": "JUAN CRUZ HERNANDEZ",
      "phone": "+525541909097",
      "email": "juan_itam@hotmail.com",
      "segment": "inactivo-30d",
      "tratamiento_principal": "PROTESIS",
      "tratamientos": [
        "Nuevo plan de tratamiento",
        "PROTESIS",
        "PANORAMICA",
        "REHABILITACION OD 14",
        "ENDODONCIA",
        "PRIMERA CONSULTA",
        "CIRUGÍA INFERIOR",
        "REHABILITACION DENTAL"
      ],
      "treatment_tag": "protesis",
      "presupuesto_total": 299574.5,
      "abonado_total": 119006,
      "deuda_total": 0,
      "reactivation_score": 105,
      "priority_band": "alta",
      "priority_reason": "inactivo-30d, protesis, presupuesto-alto, tiene-telefono",
      "elevator_id": null,
      "elevator_sync_status": null
    },
    {
      "rank": 21,
      "id": 2246,
      "nombre": "MAYRA MAYABEL GUERRERO LOPEZ",
      "phone": "+525532476809",
      "email": "mayra.mayabelguerrero@gmail.com",
      "segment": "inactivo-30d",
      "tratamiento_principal": "PROTESIS",
      "tratamientos": [
        "Nuevo plan de tratamiento",
        "PROTESIS",
        "ENDODONCIA",
        "LIMPIEZA",
        "ESTETICA DENTAL",
        "CIRUGIA",
        "CONSULTA"
      ],
      "treatment_tag": "protesis",
      "presupuesto_total": 433858.1,
      "abonado_total": 433858.1,
      "deuda_total": 0,
      "reactivation_score": 105,
      "priority_band": "alta",
      "priority_reason": "inactivo-30d, protesis, presupuesto-alto, tiene-telefono",
      "elevator_id": null,
      "elevator_sync_status": null
    },
    {
      "rank": 22,
      "id": 2562,
      "nombre": "JUAN SEBASTIAN VEGA",
      "phone": "+525554058985",
      "email": "juan.vega@ipsa-cv.com.mx",
      "segment": "inactivo-30d",
      "tratamiento_principal": "CONSULTA",
      "tratamientos": [
        "CONSULTA",
        "PROTESIS DEFINITIVA",
        "CIRUGÍA",
        "PROTESIS PROVISIONAL",
        "PRIMERA CONSULTA"
      ],
      "treatment_tag": "protesis",
      "presupuesto_total": 1047013,
      "abonado_total": 346288,
      "deuda_total": 0,
      "reactivation_score": 105,
      "priority_band": "alta",
      "priority_reason": "inactivo-30d, protesis, presupuesto-alto, tiene-telefono",
      "elevator_id": null,
      "elevator_sync_status": null
    },
    {
      "rank": 23,
      "id": 2631,
      "nombre": "NADIA FERHAD MONTIEL",
      "phone": "+525572258468",
      "email": "ferhadmontieln@gmail.com",
      "segment": "inactivo-30d",
      "tratamiento_principal": "IMPLANTOLOGÍA",
      "tratamientos": [
        "IMPLANTOLOGÍA",
        "ORTODONCIA",
        "PROTESIS",
        "ODONTOLOGIA GENERAL",
        "PRIMERA CONSULTA"
      ],
      "treatment_tag": "protesis",
      "presupuesto_total": 217963.75,
      "abonado_total": 2800,
      "deuda_total": 0,
      "reactivation_score": 105,
      "priority_band": "alta",
      "priority_reason": "inactivo-30d, protesis, presupuesto-alto, tiene-telefono",
      "elevator_id": null,
      "elevator_sync_status": null
    },
    {
      "rank": 24,
      "id": 193,
      "nombre": "PABLO GAMBOA MENDEZ",
      "phone": "+525517000329",
      "email": "pablo@indigodsn.com",
      "segment": "inactivo-90d",
      "tratamiento_principal": "LIMPIEZA DENTAL",
      "tratamientos": [
        "LIMPIEZA DENTAL",
        "ODONTOLOGIA GENERAL",
        "ORTODONCIA"
      ],
      "treatment_tag": "ortodoncia",
      "presupuesto_total": 61978,
      "abonado_total": 44692,
      "deuda_total": 17286,
      "reactivation_score": 104,
      "priority_band": "alta",
      "priority_reason": "inactivo-90d, ortodoncia, presupuesto-alto, deuda, tiene-telefono",
      "elevator_id": null,
      "elevator_sync_status": null
    },
    {
      "rank": 25,
      "id": 383,
      "nombre": "ANGELICA GOMEZ MEZA",
      "phone": "+525534947800",
      "email": "ia.angelicagomez@gmail.com",
      "segment": "inactivo-60d",
      "tratamiento_principal": "ODONTOLOGIA GENERAL",
      "tratamientos": [
        "Nuevo plan de tratamiento",
        "ODONTOLOGIA GENERAL",
        "CORONA SOBRE IMPLANTE",
        "IMPLANTOLOGIA",
        "ENDODONCIA",
        "REHABILITACION OD 24",
        "CIRUGIA OD",
        "BLANQUIAMIENTO ZOOM"
      ],
      "treatment_tag": "implantes",
      "presupuesto_total": 128593.25,
      "abonado_total": 128593.25,
      "deuda_total": 0,
      "reactivation_score": 104,
      "priority_band": "alta",
      "priority_reason": "inactivo-60d, implantes, presupuesto-alto, tiene-telefono",
      "elevator_id": null,
      "elevator_sync_status": null
    },
    {
      "rank": 26,
      "id": 1130,
      "nombre": "CARLOS ALBERTO ALCUDIA",
      "phone": "+525551043569",
      "email": "lic.alcudia@hotmail.com",
      "segment": "inactivo-60d",
      "tratamiento_principal": "CEPILLO CURAPROX",
      "tratamientos": [
        "CEPILLO CURAPROX",
        "IMPLANTOLOGIA (OD 36)",
        "CONSULTA",
        "BOTOX",
        "REHABILITACION SOBRE IMPLANTE",
        "IMPLANTOLOGIA",
        "CIRUGIA BUCAL",
        "ENDODONCIA"
      ],
      "treatment_tag": "implantes",
      "presupuesto_total": 279319,
      "abonado_total": 181674,
      "deuda_total": 0,
      "reactivation_score": 104,
      "priority_band": "alta",
      "priority_reason": "inactivo-60d, implantes, presupuesto-alto, tiene-telefono",
      "elevator_id": null,
      "elevator_sync_status": null
    },
    {
      "rank": 27,
      "id": 1708,
      "nombre": "MONICA EMMA LOPEZ",
      "phone": "+525541932340",
      "email": "monical47e@gmail.com",
      "segment": "inactivo-60d",
      "tratamiento_principal": "REHABILITACION SOBRE IMPLANTE",
      "tratamientos": [
        "REHABILITACION SOBRE IMPLANTE",
        "CIRUGIA",
        "PROTESIS",
        "ODONTOLOGIA GENERAL CORRECTO",
        "ODONTOLOGIA GENERAL",
        "REHABILITACION",
        "IMPLANTOLOGIA",
        "CIRUGÍA"
      ],
      "treatment_tag": "implantes",
      "presupuesto_total": 166631,
      "abonado_total": 41201,
      "deuda_total": 0,
      "reactivation_score": 104,
      "priority_band": "alta",
      "priority_reason": "inactivo-60d, implantes, presupuesto-alto, tiene-telefono",
      "elevator_id": null,
      "elevator_sync_status": null
    },
    {
      "rank": 28,
      "id": 1975,
      "nombre": "MARISOL HERNANDEZ",
      "phone": "+17203243890",
      "email": "solimar84@gmail.com",
      "segment": "inactivo-60d",
      "tratamiento_principal": "ODONTOLOGIA GENERAL",
      "tratamientos": [
        "ODONTOLOGIA GENERAL",
        "Nuevo plan de tratamiento",
        "LASER",
        "ENDODONCIA",
        "REHABILITACION SOBRE IMPLANTE",
        "IMPLANTOLOGIA",
        "CONSULTA",
        "BORRAR"
      ],
      "treatment_tag": "implantes",
      "presupuesto_total": 539474,
      "abonado_total": 52990,
      "deuda_total": 0,
      "reactivation_score": 104,
      "priority_band": "alta",
      "priority_reason": "inactivo-60d, implantes, presupuesto-alto, tiene-telefono",
      "elevator_id": null,
      "elevator_sync_status": null
    },
    {
      "rank": 29,
      "id": 2333,
      "nombre": "ARBELIO RODRIGUEZ",
      "phone": "+529931598658",
      "email": "robositi345@gmail.com",
      "segment": "inactivo-60d",
      "tratamiento_principal": "IMPLANTOLOGIA",
      "tratamientos": [
        "IMPLANTOLOGIA",
        "CIRUGIA",
        "ODONTOOLOGÍA GENERAL",
        "ENDODONCIA",
        "ODONTOLOGIA GENERAL",
        "Nuevo plan de tratamiento",
        "PROTESIS S/I",
        "IMPLANTES"
      ],
      "treatment_tag": "implantes",
      "presupuesto_total": 484053.75,
      "abonado_total": 92981,
      "deuda_total": 0,
      "reactivation_score": 104,
      "priority_band": "alta",
      "priority_reason": "inactivo-60d, implantes, presupuesto-alto, tiene-telefono",
      "elevator_id": null,
      "elevator_sync_status": null
    },
    {
      "rank": 30,
      "id": 2487,
      "nombre": "ELIEN RAMIREZ BARRIENTOS",
      "phone": "+525554189173",
      "email": "elienramirezcoach@gmail.com",
      "segment": "inactivo-60d",
      "tratamiento_principal": "MEDICINA ESTÉTICA",
      "tratamientos": [
        "MEDICINA ESTÉTICA",
        "ENDODONCIA",
        "ODONTOLOGIA GENERAL",
        "CIRUGÍA",
        "IMPLANTOLOGIA",
        "PROTESIS SOBRE IMPLANTES",
        "ESTETICA DENTAL",
        "PRIMERA CONSULTA"
      ],
      "treatment_tag": "implantes",
      "presupuesto_total": 683755,
      "abonado_total": 2000,
      "deuda_total": 0,
      "reactivation_score": 104,
      "priority_band": "alta",
      "priority_reason": "inactivo-60d, implantes, presupuesto-alto, tiene-telefono",
      "elevator_id": null,
      "elevator_sync_status": null
    },
    {
      "rank": 31,
      "id": 184,
      "nombre": "SARA  VELEZ",
      "phone": "+525561163612",
      "email": "rodasvelsa@gmail.com",
      "segment": "inactivo-30d",
      "tratamiento_principal": "LACER",
      "tratamientos": [
        "LACER",
        "ODONTOLOGIA GENERAL",
        "ODONTOLOGIA",
        "BOTOX",
        "ORTODONCIA",
        "ESTETICA DENTAL"
      ],
      "treatment_tag": "ortodoncia",
      "presupuesto_total": 184654.5,
      "abonado_total": 4482,
      "deuda_total": 0,
      "reactivation_score": 103,
      "priority_band": "alta",
      "priority_reason": "inactivo-30d, ortodoncia, presupuesto-alto, tiene-telefono",
      "elevator_id": null,
      "elevator_sync_status": null
    },
    {
      "rank": 32,
      "id": 345,
      "nombre": "RAFAEL TORRES MONTALVO",
      "phone": "+525529170104",
      "email": "rafael.tmontalvo@gmail.com",
      "segment": "inactivo-30d",
      "tratamiento_principal": "ODONTOLOGIA GENERAL",
      "tratamientos": [
        "Nuevo plan de tratamiento",
        "ODONTOLOGIA GENERAL",
        "REHABILITACION",
        "LIMPIEZA",
        "CIRUGIA",
        "IMPLANTOLOGIA",
        "CONSULTA Y LIMPIEZA",
        "ORTODONCIA"
      ],
      "treatment_tag": "ortodoncia",
      "presupuesto_total": 119635,
      "abonado_total": 95238,
      "deuda_total": 0,
      "reactivation_score": 103,
      "priority_band": "alta",
      "priority_reason": "inactivo-30d, ortodoncia, presupuesto-alto, tiene-telefono",
      "elevator_id": null,
      "elevator_sync_status": null
    },
    {
      "rank": 33,
      "id": 776,
      "nombre": "MARINA WOMACK",
      "phone": "+16127907024",
      "email": "eugene.sherayzen@gmail.com",
      "segment": "inactivo-30d",
      "tratamiento_principal": "ODONTOLOGIA GENERAL",
      "tratamientos": [
        "Nuevo plan de tratamiento",
        "ODONTOLOGIA GENERAL",
        "ODNTOLOGIA GENERAL",
        "ORTODONCIA",
        "CIRUGIA BUCAL"
      ],
      "treatment_tag": "ortodoncia",
      "presupuesto_total": 110094.5,
      "abonado_total": 110094.5,
      "deuda_total": 0,
      "reactivation_score": 103,
      "priority_band": "alta",
      "priority_reason": "inactivo-30d, ortodoncia, presupuesto-alto, tiene-telefono",
      "elevator_id": null,
      "elevator_sync_status": null
    },
    {
      "rank": 34,
      "id": 839,
      "nombre": "RODOLFO  ENRIQUEZ",
      "phone": "+525531455588",
      "email": "rodolfomorgado@hotmail.com",
      "segment": "inactivo-30d",
      "tratamiento_principal": "ORTODONCIA",
      "tratamientos": [
        "ORTODONCIA",
        "ODONTOLOGIA GENERAL"
      ],
      "treatment_tag": "ortodoncia",
      "presupuesto_total": 139700,
      "abonado_total": 26720,
      "deuda_total": 0,
      "reactivation_score": 103,
      "priority_band": "alta",
      "priority_reason": "inactivo-30d, ortodoncia, presupuesto-alto, tiene-telefono",
      "elevator_id": null,
      "elevator_sync_status": null
    },
    {
      "rank": 35,
      "id": 1050,
      "nombre": "DAVID RAUL BORJA GUZMAN",
      "phone": "+525544410289",
      "email": "borjazimx@yahoo.com.mx",
      "segment": "inactivo-30d",
      "tratamiento_principal": "GUARDA",
      "tratamientos": [
        "GUARDA",
        "Nuevo plan de tratamiento",
        "LIMPIEZA",
        "IMPLANTOLOGIA",
        "PRIMERA CONSULTA",
        "ORTODONCIA",
        "REHABILITACION DENTAL",
        "ENDODONCIA"
      ],
      "treatment_tag": "ortodoncia",
      "presupuesto_total": 132701,
      "abonado_total": 34468,
      "deuda_total": 0,
      "reactivation_score": 103,
      "priority_band": "alta",
      "priority_reason": "inactivo-30d, ortodoncia, presupuesto-alto, tiene-telefono",
      "elevator_id": null,
      "elevator_sync_status": null
    },
    {
      "rank": 36,
      "id": 1213,
      "nombre": "JESSICA FERNANDEZ",
      "phone": "+525522992596",
      "email": "jessica.cevallos1991@hotmail.com",
      "segment": "inactivo-30d",
      "tratamiento_principal": "LIMPIEZA",
      "tratamientos": [
        "LIMPIEZA",
        "CEPILLO CURAPROX",
        "PRIMERA CONSULTA",
        "ORTODONCIA",
        "CIRUGIA",
        "ODONTOLOGIA GENERAL"
      ],
      "treatment_tag": "ortodoncia",
      "presupuesto_total": 140169,
      "abonado_total": 5930,
      "deuda_total": 0,
      "reactivation_score": 103,
      "priority_band": "alta",
      "priority_reason": "inactivo-30d, ortodoncia, presupuesto-alto, tiene-telefono",
      "elevator_id": null,
      "elevator_sync_status": null
    },
    {
      "rank": 37,
      "id": 1604,
      "nombre": "LUIS EDUARDO  ORNELAS",
      "phone": "+525576111187",
      "email": "eduardornelas98@gmail.com",
      "segment": "inactivo-30d",
      "tratamiento_principal": "MEDICINA ESTETICA",
      "tratamientos": [
        "MEDICINA ESTETICA",
        "PRIMERA CONSULTA",
        "ORTODONCIA",
        "CIRUGÍA",
        "ODONTOLOGIA GENERAL",
        "ENDODONCIA"
      ],
      "treatment_tag": "ortodoncia",
      "presupuesto_total": 167089,
      "abonado_total": 73140,
      "deuda_total": 0,
      "reactivation_score": 103,
      "priority_band": "alta",
      "priority_reason": "inactivo-30d, ortodoncia, presupuesto-alto, tiene-telefono",
      "elevator_id": null,
      "elevator_sync_status": null
    },
    {
      "rank": 38,
      "id": 1989,
      "nombre": "BENJAMIN SALAZAR IRIARTE",
      "phone": "+525536452278",
      "email": "luisalberto.herrerab1@gmail.com",
      "segment": "inactivo-30d",
      "tratamiento_principal": "ESTETICA DENTAL",
      "tratamientos": [
        "ESTETICA DENTAL",
        "Nuevo plan de tratamiento",
        "ODONTOLOGIA GENERAL",
        "ENDODONCIA",
        "ORTODONCIA"
      ],
      "treatment_tag": "ortodoncia",
      "presupuesto_total": 405765,
      "abonado_total": 112769,
      "deuda_total": 0,
      "reactivation_score": 103,
      "priority_band": "alta",
      "priority_reason": "inactivo-30d, ortodoncia, presupuesto-alto, tiene-telefono",
      "elevator_id": null,
      "elevator_sync_status": null
    },
    {
      "rank": 39,
      "id": 2170,
      "nombre": "YATZIL REGINA VALDEZ MAGAÑA",
      "phone": "+525513076931",
      "email": "yatzilval2806@gmail.com",
      "segment": "inactivo-30d",
      "tratamiento_principal": "CONSULTA",
      "tratamientos": [
        "Nuevo plan de tratamiento",
        "CONSULTA",
        "ORTODONCIA",
        "CIRUGIA",
        "ODONTOLOGIA GENERAL"
      ],
      "treatment_tag": "ortodoncia",
      "presupuesto_total": 155617,
      "abonado_total": 78684,
      "deuda_total": 0,
      "reactivation_score": 103,
      "priority_band": "alta",
      "priority_reason": "inactivo-30d, ortodoncia, presupuesto-alto, tiene-telefono",
      "elevator_id": null,
      "elevator_sync_status": null
    },
    {
      "rank": 40,
      "id": 2393,
      "nombre": "RAUL ROJAS",
      "phone": "+525569311265",
      "email": "rulyxz@gmail.com",
      "segment": "inactivo-30d",
      "tratamiento_principal": "PERIODONCIA",
      "tratamientos": [
        "Nuevo plan de tratamiento",
        "PERIODONCIA",
        "PRIMERA CONSULTA",
        "ORTODONCIA",
        "CIRUGÍA",
        "ENDODONCIA",
        "ODONTOLOGIA GENERAL"
      ],
      "treatment_tag": "ortodoncia",
      "presupuesto_total": 236887.78,
      "abonado_total": 44927.78,
      "deuda_total": 0,
      "reactivation_score": 103,
      "priority_band": "alta",
      "priority_reason": "inactivo-30d, ortodoncia, presupuesto-alto, tiene-telefono",
      "elevator_id": null,
      "elevator_sync_status": null
    },
    {
      "rank": 41,
      "id": 2544,
      "nombre": "ISRAEL GUÍZAR CUELLAR",
      "phone": "+525549350954",
      "email": "israel.guizar@gmail.com",
      "segment": "inactivo-30d",
      "tratamiento_principal": "ORTODONCIA",
      "tratamientos": [
        "Nuevo plan de tratamiento",
        "ORTODONCIA",
        "MEDICINA ESTÉTICA",
        "ODONTOLOGIA GENERAL",
        "ENDODONCIA",
        "CIRUGIA",
        "PRIMERA CONSULTA"
      ],
      "treatment_tag": "ortodoncia",
      "presupuesto_total": 188168,
      "abonado_total": 2000,
      "deuda_total": 0,
      "reactivation_score": 103,
      "priority_band": "alta",
      "priority_reason": "inactivo-30d, ortodoncia, presupuesto-alto, tiene-telefono",
      "elevator_id": null,
      "elevator_sync_status": null
    },
    {
      "rank": 42,
      "id": 2552,
      "nombre": "IVAN ADRIAN ESPINOSA TREJO",
      "phone": "+525579833076",
      "email": "ivan.espinosa.ipn@live.com",
      "segment": "inactivo-30d",
      "tratamiento_principal": "ESTETICA DENTAL",
      "tratamientos": [
        "Nuevo plan de tratamiento",
        "ESTETICA DENTAL",
        "ORTODONCIA",
        "CIRUGIA",
        "ODONTOLOGIA GENERAL",
        "ENDODONCIA",
        "PRIMER CONSULTA"
      ],
      "treatment_tag": "ortodoncia",
      "presupuesto_total": 335119.78,
      "abonado_total": 11482.78,
      "deuda_total": 0,
      "reactivation_score": 103,
      "priority_band": "alta",
      "priority_reason": "inactivo-30d, ortodoncia, presupuesto-alto, tiene-telefono",
      "elevator_id": null,
      "elevator_sync_status": null
    },
    {
      "rank": 43,
      "id": 2601,
      "nombre": "ANGELICA ZIEBE LUBCKE",
      "phone": "+525554059827",
      "email": "kiki003@icloud.com",
      "segment": "inactivo-30d",
      "tratamiento_principal": "ORTODONCIA",
      "tratamientos": [
        "ORTODONCIA",
        "MEDICINA ESTÉTICA",
        "ODONTOLOGIA GENERAL",
        "ENDODONCIA",
        "PRIMERA CONSULTA"
      ],
      "treatment_tag": "ortodoncia",
      "presupuesto_total": 171700,
      "abonado_total": 2000,
      "deuda_total": 0,
      "reactivation_score": 103,
      "priority_band": "alta",
      "priority_reason": "inactivo-30d, ortodoncia, presupuesto-alto, tiene-telefono",
      "elevator_id": null,
      "elevator_sync_status": null
    },
    {
      "rank": 44,
      "id": 2626,
      "nombre": "ERIC CHEN",
      "phone": "+525544788812",
      "email": "erick.pw.chen@outlook.com",
      "segment": "inactivo-30d",
      "tratamiento_principal": "ORTODONCIA",
      "tratamientos": [
        "ORTODONCIA",
        "ODONTOLOGIA GENERAL",
        "Nuevo plan de tratamiento"
      ],
      "treatment_tag": "ortodoncia",
      "presupuesto_total": 180143,
      "abonado_total": 2000,
      "deuda_total": 0,
      "reactivation_score": 103,
      "priority_band": "alta",
      "priority_reason": "inactivo-30d, ortodoncia, presupuesto-alto, tiene-telefono",
      "elevator_id": null,
      "elevator_sync_status": null
    },
    {
      "rank": 45,
      "id": 2683,
      "nombre": "YUSNIER CASTELLANOS LUIS",
      "phone": "+525514191395",
      "email": "dra.lucia.ledesma@gmail.com",
      "segment": "inactivo-30d",
      "tratamiento_principal": "PRIMERA CONSULTA",
      "tratamientos": [
        "PRIMERA CONSULTA",
        "ORTODONCIA",
        "CIRUGIA BUCAL",
        "ODONTOLOGIA GENERAL"
      ],
      "treatment_tag": "ortodoncia",
      "presupuesto_total": 126235,
      "abonado_total": 3650,
      "deuda_total": 0,
      "reactivation_score": 103,
      "priority_band": "alta",
      "priority_reason": "inactivo-30d, ortodoncia, presupuesto-alto, tiene-telefono",
      "elevator_id": null,
      "elevator_sync_status": null
    },
    {
      "rank": 46,
      "id": 2687,
      "nombre": "MARIA ALICIA    GUIZAC DE LANG",
      "phone": "+52525591088414",
      "email": "aliceguizargpdl@gmail.com",
      "segment": "inactivo-30d",
      "tratamiento_principal": "ORTODONCIA",
      "tratamientos": [
        "ORTODONCIA",
        "ODONTOLOGIA GENERAL",
        "PRIMERA CONSULTA"
      ],
      "treatment_tag": "ortodoncia",
      "presupuesto_total": 127490,
      "abonado_total": 2000,
      "deuda_total": 0,
      "reactivation_score": 103,
      "priority_band": "alta",
      "priority_reason": "inactivo-30d, ortodoncia, presupuesto-alto, tiene-telefono",
      "elevator_id": null,
      "elevator_sync_status": null
    },
    {
      "rank": 47,
      "id": 1297,
      "nombre": "JULIO SALAZAR TORO",
      "phone": "+525662337214",
      "email": "jsalazartoro@gmail.com",
      "segment": "inactivo-90d",
      "tratamiento_principal": "ORTODONCIA",
      "tratamientos": [
        "ORTODONCIA",
        "Nuevo plan de tratamiento",
        "2DA CIRUGIA CUADRANTE I",
        "1ERA CIRUGIA",
        "PRIMERA CONSULTA"
      ],
      "treatment_tag": "ortodoncia",
      "presupuesto_total": 273599,
      "abonado_total": 2080,
      "deuda_total": 289,
      "reactivation_score": 102,
      "priority_band": "alta",
      "priority_reason": "inactivo-90d, ortodoncia, presupuesto-alto, deuda, tiene-telefono",
      "elevator_id": null,
      "elevator_sync_status": null
    },
    {
      "rank": 48,
      "id": 1480,
      "nombre": "NARVICK CABRAL",
      "phone": "+525510035271",
      "email": null,
      "segment": "nunca-agendo",
      "tratamiento_principal": "ESTETICA DENTAL",
      "tratamientos": [
        "ESTETICA DENTAL"
      ],
      "treatment_tag": "estetica",
      "presupuesto_total": 44224,
      "abonado_total": 0,
      "deuda_total": 0,
      "reactivation_score": 102,
      "priority_band": "alta",
      "priority_reason": "nunca-agendo, estetica, presupuesto-alto, tiene-telefono",
      "elevator_id": null,
      "elevator_sync_status": null
    },
    {
      "rank": 49,
      "id": 1613,
      "nombre": "MARIA GARCIA CEREZO",
      "phone": "+34661741170",
      "email": null,
      "segment": "nunca-agendo",
      "tratamiento_principal": "CIRUGIA",
      "tratamientos": [
        "CIRUGIA"
      ],
      "treatment_tag": "cirugia",
      "presupuesto_total": 55463,
      "abonado_total": 0,
      "deuda_total": 0,
      "reactivation_score": 102,
      "priority_band": "alta",
      "priority_reason": "nunca-agendo, cirugia, presupuesto-alto, tiene-telefono",
      "elevator_id": null,
      "elevator_sync_status": null
    },
    {
      "rank": 50,
      "id": 2297,
      "nombre": "JORGE  UDELMAN LOVERA",
      "phone": "+525532073159",
      "email": "udelmanjorge@gmail.com",
      "segment": "inactivo-30d",
      "tratamiento_principal": "REHABILITACION DE IMPLANTE",
      "tratamientos": [
        "Nuevo plan de tratamiento",
        "REHABILITACION DE IMPLANTE",
        "IMPLANTOLOGIA",
        "REHABILITACION",
        "ENDODONCIA"
      ],
      "treatment_tag": "implantes",
      "presupuesto_total": 87155,
      "abonado_total": 34308,
      "deuda_total": 0,
      "reactivation_score": 102,
      "priority_band": "alta",
      "priority_reason": "inactivo-30d, implantes, presupuesto-alto, tiene-telefono",
      "elevator_id": null,
      "elevator_sync_status": null
    }
  ]
}